anyblok_multi_engines/__init__.py
anyblok_multi_engines/config.py
anyblok_multi_engines/registry.py
anyblok_multi_engines/release.py
anyblok_multi_engines/test_bloks/__init__.py
anyblok_multi_engines/test_bloks/test1/__init__.py
anyblok_multi_engines/test_bloks/test1/test.py
anyblok_multi_engines/test_bloks/test2/__init__.py
anyblok_multi_engines/test_bloks/test2/test.py
anyblok_multi_engines/test_bloks/test3/__init__.py
anyblok_multi_engines/test_bloks/test3/test.py
anyblok_multi_engines/tests/__init__.py
anyblok_multi_engines/tests/test_blok.py
anyblok_multi_engines/tests/test_config.py
anyblok_multi_engines/tests/test_plugins.py
anyblok_multi_engines/tests/test_registry.py
anyblok_multi_engines-1.1.0.dist-info/DESCRIPTION.rst
anyblok_multi_engines-1.1.0.dist-info/METADATA
anyblok_multi_engines-1.1.0.dist-info/RECORD
anyblok_multi_engines-1.1.0.dist-info/WHEEL
anyblok_multi_engines-1.1.0.dist-info/entry_points.txt
anyblok_multi_engines-1.1.0.dist-info/metadata.json
anyblok_multi_engines-1.1.0.dist-info/top_level.txt
