Metadata-Version: 2.0
Name: anyblok-multi-engines
Version: 1.1.0
Summary: Web Server Pyramid for AnyBlok
Home-page: https://docs.anyblok-multi-engines.anyblok.org/1.1.0
Author: Jean-Sébastien Suzanne
Author-email: jssuzanne@anybox.fr
License: MPL2
Platform: UNKNOWN
Classifier: Development Status :: 4 - Beta
Classifier: Intended Audience :: Developers
Classifier: Programming Language :: Python :: 3.3
Classifier: Programming Language :: Python :: 3.4
Classifier: Programming Language :: Python :: 3.5
Classifier: Programming Language :: Python :: 3.6
Classifier: Programming Language :: Python :: 3.7
Classifier: Topic :: Software Development :: Libraries :: Python Modules
Classifier: License :: OSI Approved :: Mozilla Public License 2.0 (MPL 2.0)
Requires-Dist: anyblok
